textminer/__init__.py
textminer/cleaner.py
textminer/detector.py
textminer/summarizer.py
textminer_pro_injinsung-0.1.4.dist-info/licenses/LICENSE
textminer_pro_injinsung-0.1.4.dist-info/METADATA
textminer_pro_injinsung-0.1.4.dist-info/WHEEL
textminer_pro_injinsung-0.1.4.dist-info/top_level.txt
textminer_pro_injinsung-0.1.4.dist-info/RECORD
