Metadata-Version: 2.4
Name: textminer-pro-InjinSung
Version: 0.1.4
Summary: Advanced text mining tools for preprocessing, keyword extraction, summarization, and language detection.
Home-page: https://github.com/jagari/textminer-pro
Author: InjinSung
Author-email: 2242716@donga.ac.kr
License: MIT
Classifier: Development Status :: 3 - Alpha
Classifier: Intended Audience :: Developers
Classifier: Topic :: Text Processing :: Linguistic
Classifier: License :: OSI Approved :: MIT License
Classifier: Programming Language :: Python :: 3
Classifier: Programming Language :: Python :: 3.11
Classifier: Operating System :: OS Independent
Requires-Python: >=3.7
License-File: LICENSE
Requires-Dist: nltk>=3.8.1
Requires-Dist: scikit-learn>=1.3.2
Requires-Dist: langdetect>=1.0.9
Dynamic: author
Dynamic: author-email
Dynamic: classifier
Dynamic: description
Dynamic: description-content-type
Dynamic: home-page
Dynamic: license
Dynamic: license-file
Dynamic: requires-dist
Dynamic: requires-python
Dynamic: summary
